{
    "@class": "com.kony.gen.viz.model.component.KVizButton",
    "DNDConfig": null,
    "__parentReadjusting__": false,
    "_height_": {
        "type": "string",
        "value": "40px"
    },
    "_left_": {
        "type": "string",
        "value": "0%"
    },
    "_margin_": [
        0,
        0,
        0,
        0
    ],
    "_padding_": [
        0,
        0,
        0,
        0
    ],
    "_right_": {
        "type": "number",
        "value": ""
    },
    "_skin_": "ps4588f9413d7611e8831de1bd0e6fda5c",
    "_text_": "TOP STORIES",
    "_top_": {
        "type": "string",
        "value": "0%"
    },
    "_width_": {
        "type": "string",
        "value": "167px"
    },
    "canUpdateUI": true,
    "centery": {
        "type": "number",
        "value": ""
    },
    "containerweight": 100,
    "contentalignment": 5,
    "displaytext": true,
    "focusskin": "ps4588f9413d7611e8831de1bd0e6fda5c",
    "id": "bntHamCat1",
    "ide_onClick": "AS_Button_f32608689d6047b29b47c55f47942b8d",
    "info": null,
    "isvisible": true,
    "kuid": "d86ed2784b4b4ad9bf344cffbc11ad51",
    "name": "kony.ui.Button",
    "parent": "flxHamCats",
    "pf": "frmNewsAndWeather444c3380",
    "responsiveData": {
        "b1": {
            "centerY": {
                "type": "string",
                "value": ""
            },
            "contentAlignment": 6,
            "height": {
                "type": "string",
                "value": "40px"
            },
            "left": {
                "type": "string",
                "value": "10%"
            },
            "right": {
                "type": "string",
                "value": "10dp"
            },
            "top": {
                "type": "string",
                "value": "2dp"
            },
            "width": {
                "type": "string",
                "value": "80%"
            }
        },
        "b2": {
            "centerY": {
                "type": "string",
                "value": ""
            },
            "contentAlignment": 6,
            "height": {
                "type": "string",
                "value": "40px"
            },
            "left": {
                "type": "string",
                "value": "10%"
            },
            "right": {
                "type": "string",
                "value": "10dp"
            },
            "top": {
                "type": "string",
                "value": "2dp"
            },
            "width": {
                "type": "string",
                "value": "80%"
            }
        },
        "b3": {
            "centerY": {
                "type": "string",
                "value": ""
            },
            "contentAlignment": 6,
            "height": {
                "type": "string",
                "value": "40px"
            },
            "left": {
                "type": "string",
                "value": "10%"
            },
            "right": {
                "type": "string",
                "value": "10dp"
            },
            "top": {
                "type": "string",
                "value": "2dp"
            },
            "width": {
                "type": "string",
                "value": "80%"
            }
        },
        "b4": {
            "contentAlignment": 6,
            "left": {
                "type": "string",
                "value": ""
            },
            "right": {
                "type": "string",
                "value": "10dp"
            },
            "width": {
                "type": "string",
                "value": "80%"
            }
        }
    },
    "wType": "Button",
    "zindex": 0
}